Metadata-Version: 2.1
Name: sapython
Version: 1.1
Summary: Pacote usado para automações no SAP GUI
Home-page: UNKNOWN
Author: Ygor Seiji
License: UNKNOWN
Platform: UNKNOWN
